{
  "users": [
    {
      "id": 0,
      "username": "moharamfatema",
      "password": "123456798"
    },
    {
      "username": "someone",
      "password": "password",
      "id": 1
    },
    {
      "username": "ddssd",
      "password": "sddsds",
      "id": 2
    },
    {
      "username": "mmm",
      "password": "kkk",
      "id": 4
    },
    {
      "username": "retett",
      "password": "kFxP8EXMnB5mErJ",
      "id": 6
    },
    {
      "username": "ggg",
      "password": "kFxP8EXMnB5mErJ",
      "id": 7
    },
    {
      "username": "dfsfsd",
      "password": "ffff",
      "id": 8
    },
    {
      "username": "fdff",
      "password": "ddddd",
      "id": 9,
      "savedRecipes": {}
    },
    {
      "username": "dfsfsdfsd",
      "password": "dfdssddfs",
      "id": 10
    },
    {
      "username": "nadarabea",
      "password": "999",
      "id": 11
    },
    {
      "username": "neww",
      "password": "neww",
      "weight": [
        [
          "Date",
          "Weight"
        ],
        [
          "Mon Sep 13 2021 15:34:44 GMT+0200 (Eastern European Standard Time)",
          5
        ],
        [
          "Mon Sep 13 2021 15:44:10 GMT+0200 (Eastern European Standard Time)",
          30
        ],
        [
          "Mon Sep 13 2021 15:44:13 GMT+0200 (Eastern European Standard Time)",
          30
        ],
        [
          "Mon Sep 13 2021 15:49:27 GMT+0200 (Eastern European Standard Time)",
          50
        ],
        [
          "Mon Sep 13 2021 16:13:17 GMT+0200 (Eastern European Standard Time)",
          0
        ],
        [
          "Mon Sep 13 2021 16:17:21 GMT+0200 (Eastern European Standard Time)",
          0
        ],
        [
          "Mon Sep 13 2021 16:19:51 GMT+0200 (Eastern European Standard Time)",
          50
        ]
      ],
      "id": 12
    }
  ]
}